emforceapisdk/__init__.py
emforceapisdk/instagram.py
emforceapisdk/test.py
emforceapisdk/youtube.py
test/__init__.py
test/test.py
emforceapisdk-0.1.5.9.dist-info/METADATA
emforceapisdk-0.1.5.9.dist-info/WHEEL
emforceapisdk-0.1.5.9.dist-info/dependency_links.txt
emforceapisdk-0.1.5.9.dist-info/top_level.txt
emforceapisdk-0.1.5.9.dist-info/RECORD
