Metadata-Version: 2.1
Name: emforceapisdk
Version: 0.1.5.9
Summary: Emforce Python sdk for media api
Home-page: https://github.com/emforcernd/emforceapisdk
Author: Jimin Park
Author-email: parkjiminy@gmail.com
License: UNKNOWN
Keywords: emforce,emforceapisdk
Platform: UNKNOWN
Classifier: Programming Language :: Python :: 3
Classifier: Programming Language :: Python :: 3.2
Classifier: Programming Language :: Python :: 3.3
Classifier: Programming Language :: Python :: 3.4
Classifier: Programming Language :: Python :: 3.5
Classifier: Programming Language :: Python :: 3.6
Classifier: Programming Language :: Python :: 3.7
Requires-Python: >=3
Requires-Dist: facebook-sdk (==4.0.0rc0)
Requires-Dist: google-api-python-client (==1.8.3)
